tengods_bazi_mcp/MyLunar.py
tengods_bazi_mcp/__init__.py
tengods_bazi_mcp/shensha.py
tengods_bazi_mcp/tengods.py
tengods_bazi_mcp-0.1.3.dist-info/WHEEL
tengods_bazi_mcp-0.1.3.dist-info/entry_points.txt
tengods_bazi_mcp-0.1.3.dist-info/METADATA
tengods_bazi_mcp-0.1.3.dist-info/RECORD
